[
  {
    "citation": "56.11012",
    "agency": "MSHA",
    "title": "Protection of openings",
    "text": "Openings above, below, or near travelways shall be protected by railings or covers.",
    "category": "Fall Protection",
    "part": "56"
  },
  {
    "citation": "56.12004",
    "agency": "MSHA",
    "title": "Electrical conductors",
    "text": "Electrical conductors shall be insulated adequately.",
    "category": "Electrical",
    "part": "56"
  },
  {
    "citation": "56.20003",
    "agency": "MSHA",
    "title": "Housekeeping",
    "text": "Workplaces shall be kept clean and orderly.",
    "category": "General Safety",
    "part": "56"
  },
  {
    "citation": "56.15005",
    "agency": "MSHA",
    "title": "Safety belts and lines",
    "text": "Safety belts and lines shall be worn when persons work where there is danger of falling.",
    "category": "Fall Protection",
    "part": "56"
  },
  {
    "citation": "56.14100",
    "agency": "MSHA",
    "title": "Safety defects",
    "text": "Self-propelled mobile equipment shall be maintained in safe operating condition.",
    "category": "Mobile Equipment",
    "part": "56"
  }
]
